example_plugins/__init__.py
example_plugins/arg_print.py
example_plugins/simple_hello_world.py
pyGearBox/__init__.py
pyGearBox/executors.py
pyGearBox/manager.py
pyGearBox/plugin.py
pyGearBox/utils.py
pygearbox-1.1.2.dist-info/licenses/LICENSE
pygearbox-1.1.2.dist-info/METADATA
pygearbox-1.1.2.dist-info/WHEEL
pygearbox-1.1.2.dist-info/top_level.txt
pygearbox-1.1.2.dist-info/RECORD
