Metadata-Version: 2.4
Name: pygearbox
Version: 1.1.2
Summary: PyGearBox is a powerful, lightweight, and user-friendly plugin manager designed for Python applications
Home-page: https://github.com/toybrid/pyGearBox
Author: Arjun Thekkumadathil
Author-email: arjun@toybrid.com
License: Apache-2.0
Classifier: Programming Language :: Python :: 3
Classifier: License :: OSI Approved :: Apache Software License
Classifier: Operating System :: OS Independent
Requires-Python: >=3.6
License-File: LICENSE
Dynamic: author
Dynamic: author-email
Dynamic: classifier
Dynamic: description
Dynamic: description-content-type
Dynamic: home-page
Dynamic: license
Dynamic: license-file
Dynamic: requires-python
Dynamic: summary
